unix4summary/__init__.py
unix4summary/main.py
unix4summary/prompts.py
unix4summary-2025.12.21115644.dist-info/METADATA
unix4summary-2025.12.21115644.dist-info/WHEEL
unix4summary-2025.12.21115644.dist-info/top_level.txt
unix4summary-2025.12.21115644.dist-info/RECORD
