Metadata-Version: 2.4
Name: unix4summary
Version: 2025.12.21115644
Summary: A new package designed to facilitate the extraction of structured summaries or key information from user inputs related to Unix Fourth Edition. It processes textual prompts about Unix concepts, comman
Author-email: unix4summary <hi@eugene.plus>
License: MIT
Project-URL: Homepage, https://github.com/chigwell/unix4summary
Requires-Python: >=3.9
Requires-Dist: langchain-llm7>=0.0.0
Requires-Dist: llmatch-messages>=0.0.0
Requires-Dist: langchain-core>=0.3.0
